savcfg/__init__.py
savcfg/keyvault.py
savcfg/read.py
savcfg-0.3.1.dist-info/METADATA
savcfg-0.3.1.dist-info/WHEEL
savcfg-0.3.1.dist-info/RECORD
