Metadata-Version: 2.4
Name: savcfg
Version: 0.3.1
Summary: ConfigService implementation for SAVIA software projects
Author: Salvador Ruiz
Author-email: sruiz@gruposavia.eu
Requires-Python: >=3.11,<4.0
Classifier: Programming Language :: Python :: 3
Classifier: Programming Language :: Python :: 3.11
Classifier: Programming Language :: Python :: 3.12
Classifier: Programming Language :: Python :: 3.13
Classifier: Programming Language :: Python :: 3.14
Requires-Dist: azure-identity (>=1.25.1,<2.0.0)
Requires-Dist: azure-keyvault-certificates (>=4.10.0,<5.0.0)
Requires-Dist: azure-keyvault-keys (>=4.11.0,<5.0.0)
Requires-Dist: azure-keyvault-secrets (>=4.10.0,<5.0.0)
